tombi/__init__.py
tombi/py.typed
tombi-0.7.25.data/scripts/tombi
tombi-0.7.25.dist-info/METADATA
tombi-0.7.25.dist-info/WHEEL
tombi-0.7.25.dist-info/licenses/LICENSE
tombi-0.7.25.dist-info/RECORD
